{"constructorRef": "hill", "name": "Embassy Hill", "nationality": "British", "url": "http://en.wikipedia.org/wiki/Hill_(constructor)", "years_active": [{"year": 1975, "races": 11, "wins": 0, "podiums": 0}], "results": [{"year": 1975, "round": 3, "name": "South African Grand Prix", "driverRef": "stommelen", "forename": "Rolf", "surname": "Stommelen", "nationality": "German", "grid": 14, "position": 7, "points": 0.0, "laps": 78, "status": "Finished"}, {"year": 1975, "round": 5, "name": "Monaco Grand Prix", "driverRef": "hill", "forename": "Graham", "surname": "Hill", "nationality": "British", "grid": 0, "position": null, "points": 0.0, "laps": 0, "status": "Did not qualify"}, {"year": 1975, "round": 6, "name": "Belgian Grand Prix", "driverRef": "migault", "forename": "Fran\u00e7ois", "surname": "Migault", "nationality": "French", "grid": 22, "position": null, "points": 0.0, "laps": 57, "status": "Suspension"}, {"year": 1975, "round": 6, "name": "Belgian Grand Prix", "driverRef": "brise", "forename": "Tony", "surname": "Brise", "nationality": "British", "grid": 7, "position": null, "points": 0.0, "laps": 17, "status": "Engine"}, {"year": 1975, "round": 7, "name": "Swedish Grand Prix", "driverRef": "brise", "forename": "Tony", "surname": "Brise", "nationality": "British", "grid": 17, "position": 6, "points": 1.0, "laps": 79, "status": "+1 Lap"}, {"year": 1975, "round": 7, "name": "Swedish Grand Prix", "driverRef": "schuppan", "forename": "Vern", "surname": "Schuppan", "nationality": "Australian", "grid": 26, "position": null, "points": 0.0, "laps": 47, "status": "Transmission"}, {"year": 1975, "round": 8, "name": "Dutch Grand Prix", "driverRef": "brise", "forename": "Tony", "surname": "Brise", "nationality": "British", "grid": 7, "position": 7, "points": 0.0, "laps": 74, "status": "+1 Lap"}, {"year": 1975, "round": 8, "name": "Dutch Grand Prix", "driverRef": "jones", "forename": "Alan", "surname": "Jones", "nationality": "Australian", "grid": 17, "position": 13, "points": 0.0, "laps": 70, "status": "+5 Laps"}, {"year": 1975, "round": 9, "name": "French Grand Prix", "driverRef": "brise", "forename": "Tony", "surname": "Brise", "nationality": "British", "grid": 12, "position": 7, "points": 0.0, "laps": 54, "status": "Finished"}, {"year": 1975, "round": 9, "name": "French Grand Prix", "driverRef": "jones", "forename": "Alan", "surname": "Jones", "nationality": "Australian", "grid": 20, "position": 16, "points": 0.0, "laps": 53, "status": "+1 Lap"}, {"year": 1975, "round": 10, "name": "British Grand Prix", "driverRef": "jones", "forename": "Alan", "surname": "Jones", "nationality": "Australian", "grid": 28, "position": 10, "points": 0.0, "laps": 54, "status": "+2 Laps"}, {"year": 1975, "round": 10, "name": "British Grand Prix", "driverRef": "brise", "forename": "Tony", "surname": "Brise", "nationality": "British", "grid": 13, "position": 15, "points": 0.0, "laps": 53, "status": "Accident"}, {"year": 1975, "round": 11, "name": "German Grand Prix", "driverRef": "jones", "forename": "Alan", "surname": "Jones", "nationality": "Australian", "grid": 21, "position": 5, "points": 2.0, "laps": 14, "status": "Finished"}, {"year": 1975, "round": 11, "name": "German Grand Prix", "driverRef": "brise", "forename": "Tony", "surname": "Brise", "nationality": "British", "grid": 17, "position": null, "points": 0.0, "laps": 9, "status": "Accident"}, {"year": 1975, "round": 12, "name": "Austrian Grand Prix", "driverRef": "brise", "forename": "Tony", "surname": "Brise", "nationality": "British", "grid": 16, "position": 15, "points": 0.0, "laps": 28, "status": "+1 Lap"}, {"year": 1975, "round": 12, "name": "Austrian Grand Prix", "driverRef": "stommelen", "forename": "Rolf", "surname": "Stommelen", "nationality": "German", "grid": 25, "position": 16, "points": 0.0, "laps": 27, "status": "+2 Laps"}, {"year": 1975, "round": 13, "name": "Italian Grand Prix", "driverRef": "stommelen", "forename": "Rolf", "surname": "Stommelen", "nationality": "German", "grid": 23, "position": null, "points": 0.0, "laps": 3, "status": "Accident"}, {"year": 1975, "round": 13, "name": "Italian Grand Prix", "driverRef": "brise", "forename": "Tony", "surname": "Brise", "nationality": "British", "grid": 6, "position": null, "points": 0.0, "laps": 1, "status": "Accident"}, {"year": 1975, "round": 14, "name": "United States Grand Prix", "driverRef": "brise", "forename": "Tony", "surname": "Brise", "nationality": "British", "grid": 17, "position": null, "points": 0.0, "laps": 5, "status": "Accident"}]}