{"constructorRef": "merzario", "name": "Merzario", "nationality": "Italian", "url": "http://en.wikipedia.org/wiki/Merzario", "years_active": [{"year": 1978, "races": 16, "wins": 0, "podiums": 0}, {"year": 1979, "races": 15, "wins": 0, "podiums": 0}], "results": [{"year": 1979, "round": 1, "name": "Argentine Grand Prix", "driverRef": "merzario", "forename": "Arturo", "surname": "Merzario", "nationality": "Italian", "grid": 22, "position": null, "points": 0.0, "laps": 0, "status": "Collision"}, {"year": 1979, "round": 2, "name": "Brazilian Grand Prix", "driverRef": "merzario", "forename": "Arturo", "surname": "Merzario", "nationality": "Italian", "grid": 0, "position": null, "points": 0.0, "laps": 0, "status": "Did not qualify"}, {"year": 1979, "round": 3, "name": "South African Grand Prix", "driverRef": "merzario", "forename": "Arturo", "surname": "Merzario", "nationality": "Italian", "grid": 0, "position": null, "points": 0.0, "laps": 0, "status": "Did not qualify"}, {"year": 1979, "round": 4, "name": "United States Grand Prix West", "driverRef": "merzario", "forename": "Arturo", "surname": "Merzario", "nationality": "Italian", "grid": 22, "position": null, "points": 0.0, "laps": 13, "status": "Engine"}, {"year": 1979, "round": 5, "name": "Spanish Grand Prix", "driverRef": "merzario", "forename": "Arturo", "surname": "Merzario", "nationality": "Italian", "grid": 0, "position": null, "points": 0.0, "laps": 0, "status": "Did not qualify"}, {"year": 1979, "round": 6, "name": "Belgian Grand Prix", "driverRef": "merzario", "forename": "Arturo", "surname": "Merzario", "nationality": "Italian", "grid": 0, "position": null, "points": 0.0, "laps": 0, "status": "Did not qualify"}, {"year": 1979, "round": 7, "name": "Monaco Grand Prix", "driverRef": "brancatelli", "forename": "Gianfranco", "surname": "Brancatelli", "nationality": "Italian", "grid": 0, "position": null, "points": 0.0, "laps": 0, "status": "Did not prequalify"}, {"year": 1979, "round": 8, "name": "French Grand Prix", "driverRef": "merzario", "forename": "Arturo", "surname": "Merzario", "nationality": "Italian", "grid": 0, "position": null, "points": 0.0, "laps": 0, "status": "Did not qualify"}, {"year": 1979, "round": 9, "name": "British Grand Prix", "driverRef": "merzario", "forename": "Arturo", "surname": "Merzario", "nationality": "Italian", "grid": 0, "position": null, "points": 0.0, "laps": 0, "status": "Did not qualify"}, {"year": 1979, "round": 10, "name": "German Grand Prix", "driverRef": "merzario", "forename": "Arturo", "surname": "Merzario", "nationality": "Italian", "grid": 0, "position": null, "points": 0.0, "laps": 0, "status": "Did not qualify"}, {"year": 1979, "round": 11, "name": "Austrian Grand Prix", "driverRef": "merzario", "forename": "Arturo", "surname": "Merzario", "nationality": "Italian", "grid": 0, "position": null, "points": 0.0, "laps": 0, "status": "Did not qualify"}, {"year": 1979, "round": 12, "name": "Dutch Grand Prix", "driverRef": "merzario", "forename": "Arturo", "surname": "Merzario", "nationality": "Italian", "grid": 0, "position": null, "points": 0.0, "laps": 0, "status": "Did not qualify"}, {"year": 1979, "round": 13, "name": "Italian Grand Prix", "driverRef": "merzario", "forename": "Arturo", "surname": "Merzario", "nationality": "Italian", "grid": 0, "position": null, "points": 0.0, "laps": 0, "status": "Did not qualify"}, {"year": 1979, "round": 14, "name": "Canadian Grand Prix", "driverRef": "merzario", "forename": "Arturo", "surname": "Merzario", "nationality": "Italian", "grid": 0, "position": null, "points": 0.0, "laps": 0, "status": "Did not qualify"}, {"year": 1979, "round": 15, "name": "United States Grand Prix", "driverRef": "merzario", "forename": "Arturo", "surname": "Merzario", "nationality": "Italian", "grid": 0, "position": null, "points": 0.0, "laps": 0, "status": "Did not qualify"}, {"year": 1978, "round": 1, "name": "Argentine Grand Prix", "driverRef": "merzario", "forename": "Arturo", "surname": "Merzario", "nationality": "Italian", "grid": 20, "position": null, "points": 0.0, "laps": 9, "status": "Differential"}, {"year": 1978, "round": 2, "name": "Brazilian Grand Prix", "driverRef": "merzario", "forename": "Arturo", "surname": "Merzario", "nationality": "Italian", "grid": 0, "position": null, "points": 0.0, "laps": 0, "status": "Did not qualify"}, {"year": 1978, "round": 3, "name": "South African Grand Prix", "driverRef": "merzario", "forename": "Arturo", "surname": "Merzario", "nationality": "Italian", "grid": 26, "position": null, "points": 0.0, "laps": 39, "status": "Suspension"}, {"year": 1978, "round": 4, "name": "United States Grand Prix West", "driverRef": "merzario", "forename": "Arturo", "surname": "Merzario", "nationality": "Italian", "grid": 21, "position": null, "points": 0.0, "laps": 17, "status": "Gearbox"}, {"year": 1978, "round": 5, "name": "Monaco Grand Prix", "driverRef": "merzario", "forename": "Arturo", "surname": "Merzario", "nationality": "Italian", "grid": 0, "position": null, "points": 0.0, "laps": 0, "status": "Did not prequalify"}, {"year": 1978, "round": 6, "name": "Belgian Grand Prix", "driverRef": "merzario", "forename": "Arturo", "surname": "Merzario", "nationality": "Italian", "grid": 0, "position": null, "points": 0.0, "laps": 0, "status": "Did not prequalify"}, {"year": 1978, "round": 7, "name": "Spanish Grand Prix", "driverRef": "merzario", "forename": "Arturo", "surname": "Merzario", "nationality": "Italian", "grid": 0, "position": null, "points": 0.0, "laps": 0, "status": "Did not qualify"}, {"year": 1978, "round": 8, "name": "Swedish Grand Prix", "driverRef": "merzario", "forename": "Arturo", "surname": "Merzario", "nationality": "Italian", "grid": 22, "position": null, "points": 0.0, "laps": 62, "status": "+8 Laps"}, {"year": 1978, "round": 9, "name": "French Grand Prix", "driverRef": "merzario", "forename": "Arturo", "surname": "Merzario", "nationality": "Italian", "grid": 0, "position": null, "points": 0.0, "laps": 0, "status": "Did not qualify"}, {"year": 1978, "round": 10, "name": "British Grand Prix", "driverRef": "merzario", "forename": "Arturo", "surname": "Merzario", "nationality": "Italian", "grid": 23, "position": null, "points": 0.0, "laps": 32, "status": "Fuel system"}, {"year": 1978, "round": 11, "name": "German Grand Prix", "driverRef": "merzario", "forename": "Arturo", "surname": "Merzario", "nationality": "Italian", "grid": 0, "position": null, "points": 0.0, "laps": 0, "status": "Did not qualify"}, {"year": 1978, "round": 12, "name": "Austrian Grand Prix", "driverRef": "merzario", "forename": "Arturo", "surname": "Merzario", "nationality": "Italian", "grid": 0, "position": null, "points": 0.0, "laps": 0, "status": "Did not qualify"}, {"year": 1978, "round": 13, "name": "Dutch Grand Prix", "driverRef": "merzario", "forename": "Arturo", "surname": "Merzario", "nationality": "Italian", "grid": 26, "position": null, "points": 0.0, "laps": 40, "status": "Engine"}, {"year": 1978, "round": 14, "name": "Italian Grand Prix", "driverRef": "merzario", "forename": "Arturo", "surname": "Merzario", "nationality": "Italian", "grid": 22, "position": null, "points": 0.0, "laps": 14, "status": "Engine"}, {"year": 1978, "round": 14, "name": "Italian Grand Prix", "driverRef": "colombo", "forename": "Alberto", "surname": "Colombo", "nationality": "Italian", "grid": 0, "position": null, "points": 0.0, "laps": 0, "status": "Did not prequalify"}, {"year": 1978, "round": 15, "name": "United States Grand Prix", "driverRef": "merzario", "forename": "Arturo", "surname": "Merzario", "nationality": "Italian", "grid": 26, "position": null, "points": 0.0, "laps": 46, "status": "Gearbox"}, {"year": 1978, "round": 16, "name": "Canadian Grand Prix", "driverRef": "merzario", "forename": "Arturo", "surname": "Merzario", "nationality": "Italian", "grid": 0, "position": null, "points": 0.0, "laps": 0, "status": "Did not qualify"}]}