{"constructorRef": "shadow-matra", "name": "Shadow-Matra", "nationality": "British", "url": "http://en.wikipedia.org/wiki/Shadow_Racing_Cars", "years_active": [{"year": 1975, "races": 2, "wins": 0, "podiums": 0}], "results": [{"year": 1975, "round": 12, "name": "Austrian Grand Prix", "driverRef": "jarier", "forename": "Jean-Pierre", "surname": "Jarier", "nationality": "French", "grid": 14, "position": null, "points": 0.0, "laps": 10, "status": "Injection"}, {"year": 1975, "round": 13, "name": "Italian Grand Prix", "driverRef": "jarier", "forename": "Jean-Pierre", "surname": "Jarier", "nationality": "French", "grid": 13, "position": null, "points": 0.0, "laps": 32, "status": "Fuel pump"}]}