{"driver_standings": [{"driverRef": "prost", "forename": "Alain", "surname": "Prost", "nationality": "French", "points": 74.0, "wins": 4, "podiums": 11}, {"driverRef": "mansell", "forename": "Nigel", "surname": "Mansell", "nationality": "British", "points": 72.0, "wins": 5, "podiums": 9}, {"driverRef": "piquet", "forename": "Nelson", "surname": "Piquet", "nationality": "Brazilian", "points": 69.0, "wins": 4, "podiums": 10}, {"driverRef": "senna", "forename": "Ayrton", "surname": "Senna", "nationality": "Brazilian", "points": 55.0, "wins": 2, "podiums": 8}, {"driverRef": "johansson", "forename": "Stefan", "surname": "Johansson", "nationality": "Swedish", "points": 23.0, "wins": 0, "podiums": 4}, {"driverRef": "keke_rosberg", "forename": "Keke", "surname": "Rosberg", "nationality": "Finnish", "points": 22.0, "wins": 0, "podiums": 1}, {"driverRef": "berger", "forename": "Gerhard", "surname": "Berger", "nationality": "Austrian", "points": 17.0, "wins": 1, "podiums": 2}, {"driverRef": "alboreto", "forename": "Michele", "surname": "Alboreto", "nationality": "Italian", "points": 14.0, "wins": 0, "podiums": 1}, {"driverRef": "arnoux", "forename": "Ren\u00e9", "surname": "Arnoux", "nationality": "French", "points": 14.0, "wins": 0, "podiums": 0}, {"driverRef": "laffite", "forename": "Jacques", "surname": "Laffite", "nationality": "French", "points": 14.0, "wins": 0, "podiums": 2}, {"driverRef": "brundle", "forename": "Martin", "surname": "Brundle", "nationality": "British", "points": 8.0, "wins": 0, "podiums": 0}, {"driverRef": "jones", "forename": "Alan", "surname": "Jones", "nationality": "Australian", "points": 4.0, "wins": 0, "podiums": 0}, {"driverRef": "dumfries", "forename": "Johnny", "surname": "Dumfries", "nationality": "British", "points": 3.0, "wins": 0, "podiums": 0}, {"driverRef": "streiff", "forename": "Philippe", "surname": "Streiff", "nationality": "French", "points": 3.0, "wins": 0, "podiums": 0}, {"driverRef": "fabi", "forename": "Teo", "surname": "Fabi", "nationality": "Italian", "points": 2.0, "wins": 0, "podiums": 0}, {"driverRef": "patrese", "forename": "Riccardo", "surname": "Patrese", "nationality": "Italian", "points": 2.0, "wins": 0, "podiums": 0}, {"driverRef": "tambay", "forename": "Patrick", "surname": "Tambay", "nationality": "French", "points": 2.0, "wins": 0, "podiums": 0}, {"driverRef": "alliot", "forename": "Philippe", "surname": "Alliot", "nationality": "French", "points": 1.0, "wins": 0, "podiums": 0}, {"driverRef": "danner", "forename": "Christian", "surname": "Danner", "nationality": "German", "points": 1.0, "wins": 0, "podiums": 0}, {"driverRef": "angelis", "forename": "Elio", "surname": "de Angelis", "nationality": "Italian", "points": 0.0, "wins": 0, "podiums": 0}, {"driverRef": "berg", "forename": "Allen", "surname": "Berg", "nationality": "Canadian", "points": 0.0, "wins": 0, "podiums": 0}, {"driverRef": "boutsen", "forename": "Thierry", "surname": "Boutsen", "nationality": "Belgian", "points": 0.0, "wins": 0, "podiums": 0}, {"driverRef": "caffi", "forename": "Alex", "surname": "Caffi", "nationality": "Italian", "points": 0.0, "wins": 0, "podiums": 0}, {"driverRef": "capelli", "forename": "Ivan", "surname": "Capelli", "nationality": "Italian", "points": 0.0, "wins": 0, "podiums": 0}, {"driverRef": "cesaris", "forename": "Andrea", "surname": "de Cesaris", "nationality": "Italian", "points": 0.0, "wins": 0, "podiums": 0}, {"driverRef": "cheever", "forename": "Eddie", "surname": "Cheever", "nationality": "American", "points": 0.0, "wins": 0, "podiums": 0}, {"driverRef": "ghinzani", "forename": "Piercarlo", "surname": "Ghinzani", "nationality": "Italian", "points": 0.0, "wins": 0, "podiums": 0}, {"driverRef": "nannini", "forename": "Alessandro", "surname": "Nannini", "nationality": "Italian", "points": 0.0, "wins": 0, "podiums": 0}, {"driverRef": "palmer", "forename": "Jonathan", "surname": "Palmer", "nationality": "British", "points": 0.0, "wins": 0, "podiums": 0}, {"driverRef": "rothengatter", "forename": "Huub", "surname": "Rothengatter", "nationality": "Dutch", "points": 0.0, "wins": 0, "podiums": 0}, {"driverRef": "surer", "forename": "Marc", "surname": "Surer", "nationality": "Swiss", "points": 0.0, "wins": 0, "podiums": 0}, {"driverRef": "warwick", "forename": "Derek", "surname": "Warwick", "nationality": "British", "points": 0.0, "wins": 0, "podiums": 0}], "constructor_standings": [{"constructorRef": "williams", "name": "Williams", "nationality": "British", "points": 141.0, "wins": 9, "podiums": 19}, {"constructorRef": "mclaren", "name": "McLaren", "nationality": "British", "points": 96.0, "wins": 4, "podiums": 12}, {"constructorRef": "team_lotus", "name": "Team Lotus", "nationality": "British", "points": 58.0, "wins": 2, "podiums": 8}, {"constructorRef": "ferrari", "name": "Ferrari", "nationality": "Italian", "points": 37.0, "wins": 0, "podiums": 5}, {"constructorRef": "ligier", "name": "Ligier", "nationality": "French", "points": 29.0, "wins": 0, "podiums": 2}, {"constructorRef": "benetton", "name": "Benetton", "nationality": "Italian", "points": 19.0, "wins": 1, "podiums": 2}, {"constructorRef": "tyrrell", "name": "Tyrrell", "nationality": "British", "points": 11.0, "wins": 0, "podiums": 0}, {"constructorRef": "lola", "name": "Lola", "nationality": "British", "points": 6.0, "wins": 0, "podiums": 0}, {"constructorRef": "brabham", "name": "Brabham", "nationality": "British", "points": 2.0, "wins": 0, "podiums": 0}, {"constructorRef": "arrows", "name": "Arrows", "nationality": "British", "points": 1.0, "wins": 0, "podiums": 0}, {"constructorRef": "ags", "name": "AGS", "nationality": "French", "points": 0.0, "wins": 0, "podiums": 0}, {"constructorRef": "minardi", "name": "Minardi", "nationality": "Italian", "points": 0.0, "wins": 0, "podiums": 0}, {"constructorRef": "osella", "name": "Osella", "nationality": "Italian", "points": 0.0, "wins": 0, "podiums": 0}, {"constructorRef": "zakspeed", "name": "Zakspeed", "nationality": "German", "points": 0.0, "wins": 0, "podiums": 0}]}