{"driverRef": "cheever", "forename": "Eddie", "surname": "Cheever", "date_of_birth": "1958-01-10", "nationality": "American", "url": "http://en.wikipedia.org/wiki/Eddie_Cheever", "years_active": [{"year": 1978, "races": 3, "wins": 0, "podiums": 0}, {"year": 1980, "races": 14, "wins": 0, "podiums": 0}, {"year": 1981, "races": 15, "wins": 0, "podiums": 0}, {"year": 1982, "races": 15, "wins": 0, "podiums": 3}, {"year": 1983, "races": 15, "wins": 0, "podiums": 4}, {"year": 1984, "races": 16, "wins": 0, "podiums": 0}, {"year": 1985, "races": 16, "wins": 0, "podiums": 0}, {"year": 1986, "races": 1, "wins": 0, "podiums": 0}, {"year": 1987, "races": 16, "wins": 0, "podiums": 0}, {"year": 1988, "races": 16, "wins": 0, "podiums": 1}, {"year": 1989, "races": 16, "wins": 0, "podiums": 1}]}