{"driverRef": "watson", "forename": "John", "surname": "Watson", "date_of_birth": "1946-05-04", "nationality": "British", "url": "http://en.wikipedia.org/wiki/John_Watson_(racing_driver)", "years_active": [{"year": 1973, "races": 2, "wins": 0, "podiums": 0}, {"year": 1974, "races": 15, "wins": 0, "podiums": 0}, {"year": 1975, "races": 13, "wins": 0, "podiums": 0}, {"year": 1976, "races": 16, "wins": 1, "podiums": 3}, {"year": 1977, "races": 17, "wins": 0, "podiums": 1}, {"year": 1978, "races": 16, "wins": 0, "podiums": 3}, {"year": 1979, "races": 15, "wins": 0, "podiums": 1}, {"year": 1980, "races": 14, "wins": 0, "podiums": 0}, {"year": 1981, "races": 15, "wins": 1, "podiums": 4}, {"year": 1982, "races": 15, "wins": 2, "podiums": 5}, {"year": 1983, "races": 15, "wins": 1, "podiums": 3}, {"year": 1985, "races": 1, "wins": 0, "podiums": 0}]}